weenspace_rabbitmq/__init__.py
weenspace_rabbitmq/address_helper.py
weenspace_rabbitmq/amqp_consumer_handler.py
weenspace_rabbitmq/asyncio/__init__.py
weenspace_rabbitmq/asyncio/connection.py
weenspace_rabbitmq/asyncio/consumer.py
weenspace_rabbitmq/asyncio/environment.py
weenspace_rabbitmq/asyncio/management.py
weenspace_rabbitmq/asyncio/publisher.py
weenspace_rabbitmq/common.py
weenspace_rabbitmq/connection.py
weenspace_rabbitmq/consumer.py
weenspace_rabbitmq/delivery_context.py
weenspace_rabbitmq/entities.py
weenspace_rabbitmq/environment.py
weenspace_rabbitmq/exceptions.py
weenspace_rabbitmq/management.py
weenspace_rabbitmq/options.py
weenspace_rabbitmq/publisher.py
weenspace_rabbitmq/py.typed
weenspace_rabbitmq/qpid/proton/__init__.py
weenspace_rabbitmq/qpid/proton/_common.py
weenspace_rabbitmq/qpid/proton/_condition.py
weenspace_rabbitmq/qpid/proton/_data.py
weenspace_rabbitmq/qpid/proton/_delivery.py
weenspace_rabbitmq/qpid/proton/_endpoints.py
weenspace_rabbitmq/qpid/proton/_events.py
weenspace_rabbitmq/qpid/proton/_exceptions.py
weenspace_rabbitmq/qpid/proton/_handler.py
weenspace_rabbitmq/qpid/proton/_handlers.py
weenspace_rabbitmq/qpid/proton/_io.py
weenspace_rabbitmq/qpid/proton/_message.py
weenspace_rabbitmq/qpid/proton/_reactor.py
weenspace_rabbitmq/qpid/proton/_selectable.py
weenspace_rabbitmq/qpid/proton/_tracing.py
weenspace_rabbitmq/qpid/proton/_transport.py
weenspace_rabbitmq/qpid/proton/_url.py
weenspace_rabbitmq/qpid/proton/_utils.py
weenspace_rabbitmq/qpid/proton/_wrapper.py
weenspace_rabbitmq/qpid/proton/handlers.py
weenspace_rabbitmq/qpid/proton/py.typed
weenspace_rabbitmq/qpid/proton/reactor.py
weenspace_rabbitmq/qpid/proton/tracing.py
weenspace_rabbitmq/qpid/proton/utils.py
weenspace_rabbitmq/queues.py
weenspace_rabbitmq/ssl_configuration.py
weenspace_rabbitmq/utils.py
weenspace_rabbitmq-0.1.0.dist-info/LICENSE
weenspace_rabbitmq-0.1.0.dist-info/METADATA
weenspace_rabbitmq-0.1.0.dist-info/WHEEL
weenspace_rabbitmq-0.1.0.dist-info/RECORD
