Metadata-Version: 2.3
Name: weenspace-rabbitmq
Version: 0.1.0
Summary: WeenSpace RabbitMQ client for AMQP 1.0 - Event-driven microservices communication with OAuth2, TLS, Dead Letter Queues, and Priority Queues support
License: MIT
Keywords: rabbitmq,amqp,messaging,event-driven,microservices,queue,weenspace
Author: Thinh Huynh
Author-email: hdthinh@gmail.com
Requires-Python: >=3.13,<4.0
Classifier: Development Status :: 4 - Beta
Classifier: Intended Audience :: Developers
Classifier: License :: OSI Approved :: MIT License
Classifier: Programming Language :: Python :: 3
Classifier: Programming Language :: Python :: 3.13
Classifier: Topic :: Software Development :: Libraries :: Python Modules
Classifier: Topic :: System :: Networking
Requires-Dist: packaging (>=25.0,<26.0)
Requires-Dist: python-qpid-proton (>=0.40.0,<0.41.0)
Requires-Dist: typing-extensions (>=4.15.0,<5.0.0)
Project-URL: Homepage, https://github.com/weenspace/weenspace-rabbitmq
Project-URL: Repository, https://github.com/weenspace/weenspace-rabbitmq
